{
    "title": "Smart Waste Management System",
    "description": "Third year Cyber-Physical Systems Project",
    "category": {
        "title": "Cyber-Physical Systems Projects",
        "code": "3yp",
        "api_url": "https://api.ce.pdn.ac.lk/projects/v1/3yp/"
    },
    "project_url": "https://projects.ce.pdn.ac.lk/3yp/e19/Smart-Waste-Management-System/",
    "repo_url": "https://github.com/cepdnaclk/e19-3yp-Smart-Waste-Management-System",
    "page_url": "https://cepdnaclk.github.io/e19-3yp-Smart-Waste-Management-System",
    "api_url": "https://api.ce.pdn.ac.lk/projects/v1/3yp/E19/Smart-Waste-Management-System/",
    "thumbnail_url": "https://projects.ce.pdn.ac.lk/data/categories/3yp/thumbnail.jpg",
    "team": {
        "E/19/105": {
            "name": "Fahman M.H.M.",
            "email": "e19105@eng.pdn.ac.lk",
            "website": "",
            "github": "https://github.com/MohamedFahman",
            "linkedin": "https://www.linkedin.com/in/mhmfahman/",
            "researchgate": "",
            "api_url": "https://api.ce.pdn.ac.lk/people/v1/students/E19/105",
            "profile_image": "https://people.ce.pdn.ac.lk/images/students/e19/e19105.jpg",
            "profile_url": "https://people.ce.pdn.ac.lk/students/e19/105/"
        },
        "E/19/106": {
            "name": "Faseeh M.F.M.",
            "email": "e19106@eng.pdn.ac.lk",
            "website": "",
            "github": "",
            "linkedin": "",
            "researchgate": "",
            "api_url": "https://api.ce.pdn.ac.lk/people/v1/students/E19/106",
            "profile_image": "https://people.ce.pdn.ac.lk/images/students/e19/e19106.jpg",
            "profile_url": "https://people.ce.pdn.ac.lk/students/e19/106/"
        },
        "E/19/244": {
            "name": "Hamshica Mohanathas",
            "email": "e19244@eng.pdn.ac.lk",
            "website": "",
            "github": "",
            "linkedin": "",
            "researchgate": "",
            "api_url": "https://api.ce.pdn.ac.lk/people/v1/students/E19/244",
            "profile_image": "https://people.ce.pdn.ac.lk/images/students/e19/e19244.jpg",
            "profile_url": "https://people.ce.pdn.ac.lk/students/e19/244/"
        },
        "E/19/249": {
            "name": "Sayumi Muthukumarana",
            "email": "e19249@eng.pdn.ac.lk",
            "website": "",
            "github": "",
            "linkedin": "",
            "researchgate": "",
            "api_url": "https://api.ce.pdn.ac.lk/people/v1/students/E19/249",
            "profile_image": "https://people.ce.pdn.ac.lk/images/students/e19/e19249.jpg",
            "profile_url": "https://people.ce.pdn.ac.lk/students/e19/249/"
        },
        "E/19/205": {
            "name": "Sahan Nimantha",
            "email": "e19205@eng.pdn.ac.lk",
            "website": "",
            "github": "https://github.com/SahanNimantha99",
            "linkedin": "https://www.linkedin.com/in/sahan-nimantha-54424a222/",
            "researchgate": "",
            "api_url": "https://api.ce.pdn.ac.lk/people/v1/students/E19/205",
            "profile_image": "https://people.ce.pdn.ac.lk/images/students/e19/e19205.jpg",
            "profile_url": "https://people.ce.pdn.ac.lk/students/e19/205/"
        }
    },
    "supervisors": {
        "isurunawinne@eng.pdn.ac.lk": {
            "name": "Dr. Isuru Nawinne",
            "email": "isurunawinne@eng.pdn.ac.lk",
            "profile_url": "https://people.ce.pdn.ac.lk/staff/academic/isuru-nawinne/",
            "profile_image": "https://people.ce.pdn.ac.lk/images/staff/academic-staff/isuru-nawinne.png",
            "api_url": "https://api.ce.pdn.ac.lk/people/v1/staff/isurunawinne",
            "website": "",
            "linkedin": "https://www.linkedin.com/in/isuru-nawinne-73302833/",
            "researchgate": "https://www.researchgate.net/profile/Isuru-Nawinne",
            "google_scholar": "https://scholar.google.com/citations?hl=en&user=8qqGvuwAAAAJ"
        }
    },
    "tags": [
        "Web",
        "Embedded Systems",
        "React",
        "React Native",
        "Node js",
        "JWT",
        "JavaScript",
        "MongoDB",
        "Network Security"
    ]
}