{
    "eNumber": "E/20/455",
    "batch": "E20",
    "department": "Computer Engineering",
    "current_affiliation": "Department of Computer Engineering",
    "honorific": "Mr.",
    "full_name": "Wijesooriya Mudiyanselage Nuwan Dilshan",
    "name_with_initials": "W.M.N. Dilshan",
    "preferred_short_name": "Nuwan",
    "preferred_long_name": "Nuwan Dilshan",
    "emails": {
        "personal": {
            "name": "",
            "domain": ""
        },
        "faculty": {
            "name": "e20455",
            "domain": "eng.pdn.ac.lk"
        }
    },
    "location": "Welimada, Sri Lanka",
    "interests": [],
    "profile_image": "https://people.ce.pdn.ac.lk/images/students/e20/e20455.jpg",
    "urls": {
        "cv": "",
        "website": "",
        "linkedin": "",
        "github": "https://github.com/nuwan455",
        "facebook": "",
        "researchgate": "",
        "twitter": ""
    },
    "profile_page": "https://people.ce.pdn.ac.lk/students/e20/455/"
}