{
    "eNumber": "E/23/211",
    "batch": "E23",
    "department": "Computer Engineering",
    "current_affiliation": "Department of Computer Engineering",
    "honorific": "Miss.",
    "full_name": "Amarakoon Mudiyanselage Gayani Mahisha Madubhashinie",
    "name_with_initials": "A.M.G.Mahisha Madubhashinie",
    "preferred_short_name": "Mahisha",
    "preferred_long_name": "Mahisha Madubhashinie",
    "emails": {
        "personal": {
            "name": "mahishamadubhashinie",
            "domain": "gmail.com"
        },
        "faculty": {
            "name": "e23211",
            "domain": "eng.pdn.ac.lk"
        }
    },
    "location": "Matara",
    "interests": [
        "web development",
        "networking",
        "game development"
    ],
    "profile_image": "https://people.ce.pdn.ac.lk/images/students/e23/e23211.jpg",
    "urls": {
        "cv": "",
        "website": "",
        "linkedin": "https://www.linkedin.com/in/mahisha-madubhashinie",
        "github": "https://github.com/Mahee004",
        "facebook": "",
        "researchgate": "",
        "twitter": ""
    },
    "profile_page": "https://people.ce.pdn.ac.lk/students/e23/211/"
}