{
    "title": "Swarm Robot Monitoring System group C",
    "description": "Localization of multiple robots in real time, Video restoration at the presence of noise due to lighting conditions and degradation due to motion blur.",
    "category": {
        "title": "Image Processing Projects (CO543)",
        "code": "co543",
        "api_url": "http://api.ce.pdn.ac.lk/projects/v1/co543/"
    },
    "project_url": "https://projects.ce.pdn.ac.lk/co543/e15/Swarm-Robot-Monitoring-System-group-C/",
    "repo_url": "https://github.com/cepdnaclk/e15-co543-Swarm-Robot-Monitoring-System-group-C",
    "page_url": "#",
    "api_url": "http://api.ce.pdn.ac.lk/projects/v1/co543/E15/Swarm-Robot-Monitoring-System-group-C/",
    "thumbnail_url": "https://projects.ce.pdn.ac.lk/data/categories/co543/thumbnail.jpg"
}