{
    "eNumber": "E/21/283",
    "batch": "E21",
    "department": "Computer Engineering",
    "current_affiliation": "Department of Computer Engineering",
    "honorific": "Mr.",
    "full_name": "Pavindran Velalagan",
    "name_with_initials": "V. Pavindran",
    "preferred_short_name": "Pavi",
    "preferred_long_name": "Pavindran",
    "emails": {
        "personal": {
            "name": "pavibavi11",
            "domain": "gmail.com"
        },
        "faculty": {
            "name": "e21283",
            "domain": "eng.pdn.ac.lk"
        }
    },
    "location": "",
    "interests": [],
    "profile_image": "https://people.ce.pdn.ac.lk/images/students/e21/e21283.jpg",
    "urls": {
        "cv": "",
        "website": "",
        "linkedin": "www.linkedin.com/in/pavindran-velalagan-404646214",
        "github": "https://github.com/pavindranvelalagan",
        "facebook": "https://www.facebook.com/profile.php?id=100090378482395",
        "researchgate": "",
        "twitter": ""
    },
    "profile_page": "https://people.ce.pdn.ac.lk/students/e21/283/"
}