{
    "eNumber": "E/20/032",
    "batch": "E20",
    "department": "Computer Engineering",
    "current_affiliation": "Department of Computer Engineering, University of Peradeniya",
    "honorific": "",
    "full_name": "Bandara A.M.N.C.",
    "name_with_initials": "Bandara A.M.N.C.",
    "preferred_short_name": "Bandara A.M.N.C.",
    "preferred_long_name": "",
    "emails": {
        "personal": {
            "name": "",
            "domain": ""
        },
        "faculty": {
            "name": "e20032",
            "domain": "eng.pdn.ac.lk"
        }
    },
    "location": "",
    "interests": [],
    "profile_image": "https://people.ce.pdn.ac.lk/images/students/e20/e20032.jpg",
    "urls": {
        "cv": "",
        "website": "",
        "linkedin": "",
        "github": "",
        "facebook": "",
        "researchgate": "",
        "twitter": ""
    },
    "profile_page": "https://people.ce.pdn.ac.lk/students/e20/032/"
}