{
    "name": "Mrs. Nadeesha Adikari",
    "designation": "Lecturer",
    "page_url": "https://people.ce.pdn.ac.lk/staff/academic/nadeesha-adikari/",
    "email": "nadeeshaa@eng.pdn.ac.lk",
    "profile_image": "https://people.ce.pdn.ac.lk/images/staff/academic_staff/nadeesha-adikari.jpg",
    "urls": {
        "linkedin": "https://www.linkedin.com/in/nadeesha-adikari-48864961/",
        "google_scholar": "",
        "researchgate": "https://www.researchgate.net/profile/Nadeesha-Adikari",
        "website": "",
        "orcid": ""
    },
    "research_interests": [
        "Distributed Computing",
        "Programming Languages",
        "Software Engineering"
    ]
}