{
    "floor": "04",
    "id": "11",
    "label": "CE-04-11",
    "title": "Lecturer's Room 5",
    "contact": {
        "tele": "",
        "email": "alawatugoda@eng.pdn.ac.lk",
        "name": "Dr. Janaka Alawatugoda",
        "link": "https://people.ce.pdn.ac.lk//staff/academic/janaka-alawatugoda/"
    },
    "capacity": "N/A",
    "url": "#",
    "api_url": "https://api.ce.pdn.ac.lk/locations/v1/04/11/index.json",
    "description": [],
    "features": [],
    "tags": [
        "Staff"
    ],
    "accessibility": [
        "Staff"
    ]
}