{
    "floor": "04",
    "id": "10",
    "label": "CE-04-10",
    "title": "Lecturer's Room 4",
    "contact": {
        "tele": "",
        "email": "upuljm@eng.pdn.ac.lk",
        "name": "Dr. Upul Jayasinghe",
        "link": "https://people.ce.pdn.ac.lk/staff/academic/upul/"
    },
    "capacity": "N/A",
    "url": "#",
    "api_url": "https://api.ce.pdn.ac.lk/locations/v1/04/10/index.json",
    "description": [],
    "features": [],
    "tags": [
        "Staff"
    ],
    "accessibility": [
        "Staff"
    ]
}