{
    "eNumber": "E/20/286",
    "batch": "E20",
    "department": "Computer Engineering",
    "current_affiliation": "Department of Computer Engineering, University of Peradeniya",
    "honorific": "",
    "full_name": "Perera K.M.S.",
    "name_with_initials": "Perera K.M.S.",
    "preferred_short_name": "Perera K.M.S.",
    "preferred_long_name": "",
    "emails": {
        "personal": {
            "name": "",
            "domain": ""
        },
        "faculty": {
            "name": "e20286",
            "domain": "eng.pdn.ac.lk"
        }
    },
    "location": "",
    "interests": [],
    "profile_image": "https://people.ce.pdn.ac.lk/images/students/e20/e20286.jpg",
    "urls": {
        "cv": "",
        "website": "",
        "linkedin": "",
        "github": "",
        "facebook": "",
        "researchgate": "",
        "twitter": ""
    },
    "profile_page": "https://people.ce.pdn.ac.lk/students/e20/286/"
}