{
    "eNumber": "E/15/059",
    "batch": "E15",
    "department": "Computer Engineering",
    "current_affiliation": "",
    "honorific": "",
    "full_name": "Prageeth Savinda Bandara Dassanayake",
    "name_with_initials": "",
    "preferred_short_name": "Prageeth",
    "preferred_long_name": "Prageeth Dassanayake",
    "emails": {
        "personal": {
            "name": "prageethda",
            "domain": "gmail.com"
        },
        "faculty": {
            "name": "e15059",
            "domain": "eng.pdn.ac.lk"
        }
    },
    "location": "",
    "interests": [],
    "profile_image": "",
    "urls": {
        "cv": "",
        "website": "",
        "linkedin": "",
        "github": "https://github.com/savinda96",
        "facebook": "",
        "researchgate": "",
        "twitter": ""
    },
    "profile_page": "https://people.ce.pdn.ac.lk/students/e15/059/"
}