{
    "eNumber": "E/21/193",
    "batch": "E21",
    "department": "Computer Engineering",
    "current_affiliation": "Department of Computer Engineering, University of Peradeniya",
    "honorific": "",
    "full_name": "JAYASINGHE B.V.N.",
    "name_with_initials": "JAYASINGHE B.V.N.",
    "preferred_short_name": "Vedangi",
    "preferred_long_name": "",
    "emails": {
        "personal": {
            "name": "",
            "domain": ""
        },
        "faculty": {
            "name": "e21193",
            "domain": "eng.pdn.ac.lk"
        }
    },
    "location": "",
    "interests": [
        "Software Developing",
        "Networking",
        "AI and Machine Learning"
    ],
    "profile_image": "https://people.ce.pdn.ac.lk/images/students/e21/e21193.jpg",
    "urls": {
        "cv": "",
        "website": "",
        "linkedin": "",
        "github": "",
        "facebook": "",
        "researchgate": "",
        "twitter": ""
    },
    "profile_page": "https://people.ce.pdn.ac.lk/students/e21/193/"
}