{
    "eNumber": "E/20/363",
    "batch": "E20",
    "department": "Computer Engineering",
    "current_affiliation": "Department of Computer Engineering",
    "honorific": "Mr.",
    "full_name": "Senanayakage Don Yohan Vidusara Senanayake",
    "name_with_initials": "S.D.Y.V Senanayake",
    "preferred_short_name": "Yohan",
    "preferred_long_name": "Yohan Senanayake",
    "emails": {
        "personal": {
            "name": "yohansenanayake4321",
            "domain": "gmail.com"
        },
        "faculty": {
            "name": "e20363",
            "domain": "eng.pdn.ac.lk"
        }
    },
    "location": "Colombo",
    "interests": [
        "Signal Processing",
        "Artificial Intelligence",
        "Embedded Systems"
    ],
    "profile_image": "https://people.ce.pdn.ac.lk/images/students/e20/e20363.jpg",
    "urls": {
        "cv": "",
        "website": "",
        "linkedin": "",
        "github": "https://github.com/Yohansenanayake",
        "facebook": "https://www.facebook.com/profile.php?id=100010420334318",
        "researchgate": "",
        "twitter": ""
    },
    "profile_page": "https://people.ce.pdn.ac.lk/students/e20/363/"
}