{
    "eNumber": "E/19/091",
    "batch": "E19",
    "department": "Computer Engineering",
    "current_affiliation": "Department of Computer Engineering, University of Peradeniya",
    "honorific": "",
    "full_name": "Dissanayake P.A.M.",
    "name_with_initials": "Dissanayake P.A.M.",
    "preferred_short_name": "Pasan",
    "preferred_long_name": "",
    "emails": {
        "personal": {
            "name": "",
            "domain": ""
        },
        "faculty": {
            "name": "e19091",
            "domain": "eng.pdn.ac.lk"
        }
    },
    "location": "",
    "interests": [
        "AI",
        "Machine learning",
        "Web designing"
    ],
    "profile_image": "https://people.ce.pdn.ac.lk/images/students/e19/e19091.jpg",
    "urls": {
        "cv": "",
        "website": "",
        "linkedin": "",
        "github": "",
        "facebook": "",
        "researchgate": "",
        "twitter": ""
    },
    "profile_page": "https://people.ce.pdn.ac.lk/students/e19/091/"
}