{
    "e19-co226-library-management-system": {
        "title": "library management system",
        "description": "",
        "category": {
            "title": "Database Projects (CO226)",
            "code": "co226",
            "api_url": "https://api.ce.pdn.ac.lk/projects/v1/co226/"
        },
        "project_url": "https://projects.ce.pdn.ac.lk/co226/e19/library-management-system/",
        "repo_url": "https://github.com/cepdnaclk/e19-co226-library-management-system",
        "page_url": "#",
        "api_url": "https://api.ce.pdn.ac.lk/projects/v1/co226/E19/library-management-system/"
    }
}